tests/__init__.py
tests/conf.py
tests/test_cli.py
tests/test_config.py
tests/test_replacer_pipfile.py
tests/test_replacer_regex.py
tests/test_search.py
tests/test_shell_runner.py
tests/test_utils.py
update_package_version/__init__.py
update_package_version/__main__.py
update_package_version/base.py
update_package_version/cli.py
update_package_version/config.py
update_package_version/constants.py
update_package_version/exceptions.py
update_package_version/search.py
update_package_version/shell_runner.py
update_package_version/utils.py
update_package_version/replacers/__init__.py
update_package_version/replacers/pipfile.py
update_package_version/replacers/regex.py
update_package_version-0.1.3.dist-info/METADATA
update_package_version-0.1.3.dist-info/WHEEL
update_package_version-0.1.3.dist-info/entry_points.txt
update_package_version-0.1.3.dist-info/top_level.txt
update_package_version-0.1.3.dist-info/RECORD
