Metadata-Version: 2.1
Name: update-package-version
Version: 0.1.3
Summary: A python executable that delivers a path-wide version bump feature
Home-page: https://github.com/night-crawler/update-package-version
Author: night-crawler
Author-email: lilo.panic@gmail.com
License: MIT
Platform: UNKNOWN
Classifier: Environment :: Web Environment
Classifier: Intended Audience :: Developers
Classifier: Operating System :: OS Independent
Classifier: Programming Language :: Python
Classifier: Programming Language :: Python :: 3
Classifier: Programming Language :: Python :: 3.6
Classifier: License :: OSI Approved :: MIT License
Requires-Python: >=3.6
Requires-Dist: fire
Requires-Dist: pyyaml
Requires-Dist: toml
